[
  {
    "label": "MC (\u03bb=1.0)",
    "td_lambda": null,
    "final": 103.45841069329137,
    "best": 125.21499889311721,
    "time": 2595.3,
    "evals": [
      {
        "episode": 50,
        "eval": -213.69454114862475
      },
      {
        "episode": 100,
        "eval": -143.71557952442078
      },
      {
        "episode": 150,
        "eval": -95.14827277286608
      },
      {
        "episode": 200,
        "eval": -129.88411554668394
      },
      {
        "episode": 250,
        "eval": -83.4259179901147
      },
      {
        "episode": 300,
        "eval": -62.60430773470101
      },
      {
        "episode": 350,
        "eval": -84.50000908620417
      },
      {
        "episode": 400,
        "eval": -57.49660945967342
      },
      {
        "episode": 450,
        "eval": -28.303216478247908
      },
      {
        "episode": 500,
        "eval": -35.98032653801866
      },
      {
        "episode": 550,
        "eval": -22.48418846451791
      },
      {
        "episode": 600,
        "eval": -34.43264819055277
      },
      {
        "episode": 650,
        "eval": -30.077543434270304
      },
      {
        "episode": 700,
        "eval": -20.820799052581393
      },
      {
        "episode": 750,
        "eval": -18.634192081511667
      },
      {
        "episode": 800,
        "eval": 39.97685201596337
      },
      {
        "episode": 850,
        "eval": 47.36303983701593
      },
      {
        "episode": 900,
        "eval": 125.21499889311721
      },
      {
        "episode": 950,
        "eval": 81.55621393491523
      },
      {
        "episode": 1000,
        "eval": 76.60516092801478
      }
    ]
  },
  {
    "label": "\u03bb=0.9",
    "td_lambda": 0.9,
    "final": -75.09088576923851,
    "best": 18.321076607153636,
    "time": 2960.7,
    "evals": [
      {
        "episode": 50,
        "eval": -205.89407351038898
      },
      {
        "episode": 100,
        "eval": -176.47700356785214
      },
      {
        "episode": 150,
        "eval": -120.78344503279106
      },
      {
        "episode": 200,
        "eval": -114.40295415871253
      },
      {
        "episode": 250,
        "eval": -122.12104803504562
      },
      {
        "episode": 300,
        "eval": -178.44465662704272
      },
      {
        "episode": 350,
        "eval": -12.505008692403877
      },
      {
        "episode": 400,
        "eval": 18.321076607153636
      },
      {
        "episode": 450,
        "eval": -0.6923258152065402
      },
      {
        "episode": 500,
        "eval": -73.146446173396
      },
      {
        "episode": 550,
        "eval": -97.46713310621809
      },
      {
        "episode": 600,
        "eval": -69.17966265936516
      },
      {
        "episode": 650,
        "eval": -46.677215831957
      },
      {
        "episode": 700,
        "eval": -58.07775620114764
      },
      {
        "episode": 750,
        "eval": -59.90126920569926
      },
      {
        "episode": 800,
        "eval": -55.662161453750855
      },
      {
        "episode": 850,
        "eval": -49.17672835797017
      },
      {
        "episode": 900,
        "eval": -35.670068224173136
      },
      {
        "episode": 950,
        "eval": -30.586625745685957
      },
      {
        "episode": 1000,
        "eval": -37.57776784521695
      }
    ]
  }
]